[
  {
    "ref": "8d56a16e-ed97-4f98-9309-d755ec034942",
    "keyword": "e9b3c252697e2a2edab33892a988f290",
    "answer": "Hey",
    "options": {},
    "from": "573185215524",
    "refSerialize": "277c8cb949f2e3dbc96f9369fddf7be3"
  },
  {
    "ref": "ans_21cb1416-ec2e-4b2f-ac16-1c1e3b02869a",
    "keyword": "key_4d5687b3-c897-4931-a635-c1379bf46cb8",
    "answer": "__call_action__",
    "options": {
      "media": null,
      "buttons": [],
      "capture": false,
      "child": null,
      "delay": 0,
      "idle": null,
      "ref": null,
      "nested": [],
      "keyword": {},
      "callback": true
    },
    "refSerialize": "809792061d96ee856db1470def9cdc4a",
    "from": "573185215524"
  },
  {
    "ref": "bb13c838-21ca-47b2-948d-0fccefd1072e",
    "keyword": null,
    "answer": "隆Buenos d铆as, Andres G!  Soy Conny, fundadora de Solteros y Parceros \nGracias por empezar tu d铆a con nosotros \nEn nuestras redes como Instagram y TikTok conectamos a corazones libres \nY tambi茅n ofrecemos espacios para que las marcas se hagan notar ",
    "options": {
      "media": null,
      "buttons": [],
      "capture": false,
      "delay": 0
    },
    "from": "573185215524",
    "refSerialize": "5a32e0905ace47165280f1e62fc735f2"
  },
  {
    "ref": "ans_87386f66-aac5-4547-ac54-63d715a51b1b",
    "keyword": "ans_21cb1416-ec2e-4b2f-ac16-1c1e3b02869a",
    "answer": "Por favor, elige la opci贸n que m谩s te interese \n\n*1*. Pauta Empresas\n*2*. Presentando solteros (con o sin foto)\n*3*. Historias\n*4*. Entrevista Presencial\n",
    "options": {
      "media": null,
      "buttons": [],
      "capture": true,
      "child": null,
      "delay": 0,
      "idle": null,
      "ref": null,
      "nested": [],
      "keyword": {},
      "callback": true
    },
    "refSerialize": "16e2ca6ab719f7630a818f804c4bb1e3",
    "from": "573185215524"
  },
  {
    "ref": "817a09f9-534c-4325-91fe-5a5cb356eaba",
    "keyword": "16e2ca6ab719f7630a818f804c4bb1e3",
    "answer": "3",
    "options": {},
    "from": "573185215524",
    "refSerialize": "7af65864494b12f0f7ef00589f4d3979"
  },
  {
    "ref": "18266d59-9f42-4f72-9a7d-dfd245ee1d73",
    "keyword": null,
    "answer": " *Sobre Nosotros*\n\nSomos una empresa dedicada a proporcionar soluciones innovadoras para nuestros clientes. Fundada en 2010, hemos crecido constantemente gracias a la confianza de nuestros usuarios.\n\nNuestra misi贸n es ofrecer servicios de alta calidad con atenci贸n personalizada.",
    "options": {
      "media": null,
      "buttons": [],
      "capture": false,
      "delay": 0
    },
    "from": "573185215524",
    "refSerialize": "c1559a139b2d1581a7a29b60785faba9"
  },
  {
    "ref": "ans_d83e46d3-01d7-4d0a-9008-08b2fd0615f6",
    "keyword": "key_9ddfbb7a-4abe-4c49-b55a-c6c1f5c8e277",
    "answer": "__call_action__",
    "options": {
      "media": null,
      "buttons": [],
      "capture": false,
      "child": null,
      "delay": 0,
      "idle": null,
      "ref": null,
      "nested": [],
      "keyword": {},
      "callback": true
    },
    "from": "573185215524"
  },
  {
    "ref": "ans_97aef152-a79b-484b-a04c-0bfcf2587e5a",
    "keyword": "ans_d83e46d3-01d7-4d0a-9008-08b2fd0615f6",
    "answer": "Por favor, elige la opci贸n que m谩s te interese \n\n*1*. Pauta Empresas\n*2*. Presentando solteros (con o sin foto)\n*3*. Historias\n*4*. Entrevista Presencial\n",
    "options": {
      "media": null,
      "buttons": [],
      "capture": true,
      "child": null,
      "delay": 0,
      "idle": null,
      "ref": null,
      "nested": [],
      "keyword": {},
      "callback": true
    },
    "from": "573185215524"
  }
]